gguf_parser/__init__.py
gguf_parser/__main__.py
gguf_parser/gguf_parser.py
tests/__init__.py
tests/test_gguf_parser.py
gguf_parser-0.1.1.dist-info/LICENSE
gguf_parser-0.1.1.dist-info/METADATA
gguf_parser-0.1.1.dist-info/WHEEL
gguf_parser-0.1.1.dist-info/top_level.txt
gguf_parser-0.1.1.dist-info/RECORD
