Metadata-Version: 2.1
Name: gguf-parser
Version: 0.1.1
Summary: A parser for GGUF files
Home-page: https://github.com/hirox/gguf-parser
Author: Hiromichi Goto
Author-email: goto@suzuca.ai
Classifier: Development Status :: 3 - Alpha
Classifier: Intended Audience :: Developers
Classifier: License :: OSI Approved :: Apache Software License
Classifier: Programming Language :: Python :: 3
Classifier: Programming Language :: Python :: 3.6
Classifier: Programming Language :: Python :: 3.7
Classifier: Programming Language :: Python :: 3.8
Classifier: Programming Language :: Python :: 3.9
Requires-Python: >=3.6
License-File: LICENSE
Requires-Dist: argparse
